odoo/addons/base_iso3166/README.rst
odoo/addons/base_iso3166/__init__.py
odoo/addons/base_iso3166/__manifest__.py
odoo/addons/base_iso3166/i18n/base_iso3166.pot
odoo/addons/base_iso3166/i18n/es.po
odoo/addons/base_iso3166/i18n/hr.po
odoo/addons/base_iso3166/i18n/it.po
odoo/addons/base_iso3166/i18n/nl.po
odoo/addons/base_iso3166/i18n/tr.po
odoo/addons/base_iso3166/models/__init__.py
odoo/addons/base_iso3166/models/res_country.py
odoo/addons/base_iso3166/readme/CONTRIBUTORS.md
odoo/addons/base_iso3166/readme/DESCRIPTION.md
odoo/addons/base_iso3166/readme/INSTALL.md
odoo/addons/base_iso3166/readme/ROADMAP.md
odoo/addons/base_iso3166/readme/USAGE.md
odoo/addons/base_iso3166/static/description/icon.png
odoo/addons/base_iso3166/static/description/icon.svg
odoo/addons/base_iso3166/static/description/index.html
odoo/addons/base_iso3166/tests/__init__.py
odoo/addons/base_iso3166/tests/test_iso3166.py
odoo/addons/base_iso3166/views/country_view.xml
odoo_addon_base_iso3166-18.0.1.0.0.5.dist-info/METADATA
odoo_addon_base_iso3166-18.0.1.0.0.5.dist-info/WHEEL
odoo_addon_base_iso3166-18.0.1.0.0.5.dist-info/top_level.txt
odoo_addon_base_iso3166-18.0.1.0.0.5.dist-info/RECORD
