Metadata-Version: 2.1
Name: odoo-addon-base_iso3166
Version: 18.0.1.0.0.5
Requires-Python: >=3.10
Requires-Dist: odoo==18.0.*
Requires-Dist: pycountry
Summary: ISO 3166
Home-page: https://github.com/OCA/community-data-files
License: AGPL-3
Author: Tecnativa, Creu Blanca, Odoo Community Association (OCA)
Author-email: support@odoo-community.org
Classifier: Programming Language :: Python
Classifier: Framework :: Odoo
Classifier: Framework :: Odoo :: 18.0
Classifier: License :: OSI Approved :: GNU Affero General Public License v3
Classifier: Development Status :: 5 - Production/Stable
